advhash/__init__.py
advhash/hashes.py
advhash/attack/__init__.py
advhash/attack/base.py
advhash/attack/hinge.py
advhash/attack/l2.py
advhash/hash/__init__.py
advhash/hash/base.py
advhash/hash/dhash.py
advhash/utils/__init__.py
advhash/utils/compare.py
advhash/utils/constrain.py
advhash/utils/convert.py
advhash/utils/generic.py
advhash/utils/resize.py
advhash-0.1.1.dist-info/LICENSE
advhash-0.1.1.dist-info/METADATA
advhash-0.1.1.dist-info/WHEEL
advhash-0.1.1.dist-info/top_level.txt
advhash-0.1.1.dist-info/RECORD
