Metadata-Version: 2.1
Name: advhash
Version: 0.1.1
Summary: Adversarial attacks for perceptual image hashing functions
Home-page: https://github.com/mattpodolak/advhash
Author: Matthew Podolak
Author-email: mpodola2@gmail.com
License: GNU GPLv3
Keywords: adversarial attacks image hashing
Platform: UNKNOWN
Classifier: Development Status :: 3 - Alpha
Classifier: Programming Language :: Python :: 3 :: Only
Classifier: Programming Language :: Python :: 3.5
Classifier: Programming Language :: Python :: 3.6
Classifier: Programming Language :: Python :: 3.7
Classifier: Programming Language :: Python :: 3.8
Classifier: Programming Language :: Python :: 3.9
Classifier: Intended Audience :: Science/Research
Classifier: Topic :: Scientific/Engineering
Classifier: License :: OSI Approved :: GNU General Public License v3 (GPLv3)
Classifier: Operating System :: OS Independent
Requires-Python: >=3.5
License-File: LICENSE
Requires-Dist: torch (>=1.8.1)
Requires-Dist: numpy (>=1.19.2)
Requires-Dist: tqdm (==4.61.0)
